tablebase.cp39-win_amd64.pyd
krk_tablebase_generator-0.0.1.dist-info/LICENSE.txt
krk_tablebase_generator-0.0.1.dist-info/METADATA
krk_tablebase_generator-0.0.1.dist-info/WHEEL
krk_tablebase_generator-0.0.1.dist-info/top_level.txt
krk_tablebase_generator-0.0.1.dist-info/RECORD
