Metadata-Version: 2.1
Name: krk-tablebase-generator
Version: 0.0.1
Summary: C++ extension package that generates a tablebase of KR_K chess endgames.
Author: Nolan Chu
Author-email: nolan.chu.2012@gmail.com
License: UNKNOWN
Platform: UNKNOWN
Classifier: Programming Language :: Python :: 3
Classifier: License :: OSI Approved :: MIT License
License-File: LICENSE.txt
